jumpstarter_driver_network/__init__.py
jumpstarter_driver_network/client.py
jumpstarter_driver_network/conftest.py
jumpstarter_driver_network/driver.py
jumpstarter_driver_network/driver_test.py
jumpstarter_driver_network/py.typed
jumpstarter_driver_network/adapters/__init__.py
jumpstarter_driver_network/adapters/dbus.py
jumpstarter_driver_network/adapters/fabric.py
jumpstarter_driver_network/adapters/fabric_test.py
jumpstarter_driver_network/adapters/novnc.py
jumpstarter_driver_network/adapters/novnc_test.py
jumpstarter_driver_network/adapters/pexpect.py
jumpstarter_driver_network/adapters/portforward.py
jumpstarter_driver_network/streams/__init__.py
jumpstarter_driver_network/streams/websocket.py
jumpstarter_driver_network-0.7.4.dist-info/METADATA
jumpstarter_driver_network-0.7.4.dist-info/WHEEL
jumpstarter_driver_network-0.7.4.dist-info/entry_points.txt
jumpstarter_driver_network-0.7.4.dist-info/RECORD
