Metadata-Version: 2.4
Name: jumpstarter-driver-network
Version: 0.7.4
Project-URL: Homepage, https://jumpstarter.dev
Project-URL: source_archive, https://github.com/jumpstarter-dev/repo/archive/c5d38de69eadbb8eb0388bcfe3430a679fff0059.zip
Author-email: Miguel Angel Ajo Pelayo <majopela@redhat.com>, Nick Cao <ncao@redhat.com>
License-Expression: Apache-2.0
Requires-Python: >=3.11
Requires-Dist: click>=8.1.8
Requires-Dist: fabric>=3.2.2
Requires-Dist: jumpstarter==0.7.4
Requires-Dist: pexpect>=4.9.0
Requires-Dist: websockets>=15.0.1
Requires-Dist: wsproto>=1.2.0
